pyleaves/__init__.py
pyleaves/leaves.py
pyleaves/text_format.py
pyleaves/utils.py
pyleaves/PyroTools/__init__.py
pyleaves/PyroTools/progress_message.py
PyLeaves-1.0.3.dist-info/LICENSE
PyLeaves-1.0.3.dist-info/METADATA
PyLeaves-1.0.3.dist-info/WHEEL
PyLeaves-1.0.3.dist-info/top_level.txt
PyLeaves-1.0.3.dist-info/RECORD
